pywhere39/__init__.py
pywhere39/cli.py
pywhere39/pywhere39.py
pywhere39/wordlist.py
pywhere39-0.0.1.dist-info/LICENSE
pywhere39-0.0.1.dist-info/WHEEL
pywhere39-0.0.1.dist-info/METADATA
pywhere39-0.0.1.dist-info/RECORD
